overlink/__init__.py
overlink/client.py
overlink/server.py
overlink/utils.py
overlink-0.4.0.dist-info/METADATA
overlink-0.4.0.dist-info/WHEEL
overlink-0.4.0.dist-info/top_level.txt
overlink-0.4.0.dist-info/RECORD
