Metadata-Version: 2.4
Name: overlink
Version: 0.4.0
Summary: Bridge between local PC and cloud GPU processing
Home-page: https://github.com/KhanhRomVN/overlink
Author: KhanhRomVN
Author-email: KhanhRomVN <khanhromvn@gmail.com>
Project-URL: Homepage, https://github.com/KhanhRomVN/overlink
Project-URL: Bug Tracker, https://github.com/KhanhRomVN/overlink/issues
Classifier: Programming Language :: Python :: 3
Classifier: License :: OSI Approved :: MIT License
Classifier: Operating System :: OS Independent
Requires-Python: >=3.6
Dynamic: author
Dynamic: home-page
Dynamic: requires-python
